sanber_geometry/__init__.py
sanber_geometry/lingkaran.py
sanber_geometry/persegi.py
sanber_training/__init__.py
sanbercode_geometry-0.0.3.dist-info/LICENSE.txt
sanbercode_geometry-0.0.3.dist-info/METADATA
sanbercode_geometry-0.0.3.dist-info/WHEEL
sanbercode_geometry-0.0.3.dist-info/top_level.txt
sanbercode_geometry-0.0.3.dist-info/RECORD
