Metadata-Version: 2.1
Name: sanbercode-geometry
Version: 0.0.3
Summary: geometry package tugas sanbercode
Home-page: https://github.com/putuhendrawd/sanbercode_geometry
Author: putuhendrawd
Author-email: putuhendrawd@gmail.com
Classifier: Programming Language :: Python :: 3
Classifier: License :: OSI Approved :: MIT License
Classifier: Operating System :: OS Independent
Requires-Python: >=3.9
License-File: LICENSE.txt
Requires-Dist: numpy (>=1.21)
Requires-Dist: matplotlib (>=3.7.2)
